data_structure_helpers/__init__.py
data_structure_helpers/dict_helpers.py
data_structure_helpers/linked_list.py
data_structure_helpers/linked_list_node.py
data_structure_helpers/list_helpers.py
data_structure_helpers/string_helpers.py
data_structure_helpers/tree.py
data_structure_helpers/tests/__init__.py
data_structure_helpers/tests/test_dict_helpers.py
data_structure_helpers/tests/test_linked_list.py
data_structure_helpers/tests/test_linked_list_node.py
data_structure_helpers/tests/test_list_helpers.py
data_structure_helpers/tests/test_string_helpers.py
data_structure_helpers/tests/test_tree.py
ctodd_python_lib_data_structures-1.0.0.dist-info/LICENSE
ctodd_python_lib_data_structures-1.0.0.dist-info/METADATA
ctodd_python_lib_data_structures-1.0.0.dist-info/WHEEL
ctodd_python_lib_data_structures-1.0.0.dist-info/top_level.txt
ctodd_python_lib_data_structures-1.0.0.dist-info/RECORD
