Metadata-Version: 2.1
Name: ctodd-python-lib-data-structures
Version: 1.0.0
Summary: Python utilities used for interacting with Python Data Structures
Home-page: https://github.com/ChristopherHaydenTodd/ctodd-python-lib-data-structures
Author: Christopher H. Todd
Author-email: Christopher.Hayden.Todd@gmail.com
License: MIT
Keywords: python,libraries
Platform: UNKNOWN
Classifier: Development Status :: 5 - Production/Stable
Classifier: Intended Audience :: Developers
Classifier: Natural Language :: English
Classifier: Programming Language :: Python
Classifier: Programming Language :: Python :: 3
Classifier: Programming Language :: Python :: 3.6
Classifier: Programming Language :: Python :: 3.7
Classifier: Programming Language :: Python :: 3.8
Requires-Python: >3.6
Requires-Dist: anytree (>=2.6.0)
